lightdict/__init__.py
lightdict/component/__init__.py
lightdict/component/character.py
lightdict/component/dictionary.py
lightdict/component/word.py
lightdict/utils/__init__.py
lightdict/utils/common.py
lightDict-0.1.0.dist-info/LICENSE
lightDict-0.1.0.dist-info/METADATA
lightDict-0.1.0.dist-info/WHEEL
lightDict-0.1.0.dist-info/top_level.txt
lightDict-0.1.0.dist-info/RECORD
